<?xml version="1.0" encoding="utf-8"?>
<form addrulepath="/administrator/components/com_projects/models/rules">
    <fieldset name="names">
        <field
                name="id"
                type="hidden"
        />
        <field
                name="title"
                type="text"
                label="COM_PROJECTS_FILTER_CATALOG"
                description="COM_PROJECTS_FILTER_CATALOG"
                hint="COM_PROJECTS_FILTER_CATALOG_HINT"
                autocomplete="off"
                class="x2"
                required="true"
        />
        <field
                name="tip"
                label="COM_PROJECTS_HEAD_CONTRACT_CATALOG_TYPE"
                description="COM_PROJECTS_HEAD_CONTRACT_CATALOG_TYPE_DESC"
                type="list"
                class="x2"
                required="true"
                default="0">
            <option value="0">COM_PROJECTS_HEAD_CONTRACT_CATALOG_TYPE_0</option>
            <option value="1">COM_PROJECTS_HEAD_CONTRACT_CATALOG_TYPE_1</option>
            <option value="2">COM_PROJECTS_HEAD_CONTRACT_CATALOG_TYPE_2</option>
        </field>
    </fieldset>
</form>